{
  "triggers": [
    {
      "type": "setvalue",
      "expression": "{send-results} = true",
      "setToName": "code",
      "setValue": "Feedback-Install-Checklist"
    }
  ],
  "pages": [
    {
      "name": "install-method",
      "elements": [
        {
          "type": "radiogroup",
          "name": "install-type",
          "title": {
            "default": "Which method of the install are you trying to make?",
            "nb": "Hvilken metode for installasjonen prøver du å gjøre?"
          },
          "isRequired": true,
          "colCount": 1,
          "choices": [
            {
              "value": "manual",
              "text": {
                "default": "Manual - Download and install using install guide",
                "nb": "Manual - Last ned og installer ved hjelp av installasjonsveiledningen"
              }
            },
            {
              "value": "automated",
              "text": {
                "default": "Automated - Download and using command line interface",
                "nb": "Automatisert - Last ned og bruk kommandolinjegrensesnitt"
              }
            }
          ]
        },
        {
          "type": "html",
          "visibleIf": "{install-type} == 'manual'",
          "html": {
            "default": "Manual install selected. Using this install you will download the [release from GitHub](https://github.com/microsoft/powercat-automation-kit/releases) and follow steps from <a href='https://learn.microsoft.com/power-automate/guidance/automation-kit/setup/prerequisites' target='_blank'>online install instructions</a> to install and configure the solution. Use the next pages as a checklist for the manual install process",
            "nb": "Manuell installasjon valgt. Ved hjelp av denne installasjonen vil du laste ned [utgivelse fra GitHub](https://github.com/microsoft/powercat-automation-kit/releases) og følg trinnene fra <a href='https://learn.microsoft.com/power-automate/guidance/automation-kit/setup/prerequisites' target='_blank'>Installasjonsinstruksjoner på Internett</a> for å installere og konfigurere løsningen. Bruk de neste sidene som sjekkliste for den manuelle installasjonsprosessen"
          }
        },
        {
          "type": "html",
          "visibleIf": "{install-type} == 'automated'",
          "html": {
            "default": "Automated install selected. Use the  <a href='/get-started/install' target='_blank'>install guide</a> to download the install ZIP file from [GitHub](https://github.com/microsoft/powercat-automation-kit/releases) and then use the command line to automate the setup and configuration of the solution",
            "nb": "Automatisert installasjon valgt. Bruk ikonet  <a href='/get-started/install' target='_blank'>Veiledning for installasjon</a> for å laste ned installasjons-ZIP-filen fra [GitHub](https://github.com/microsoft/powercat-automation-kit/releases) og bruk deretter kommandolinjen til å automatisere oppsettet og konfigurasjonen av løsningen"
          }
        }
      ]
    },
    {
      "name": "welcome",
      "visibleIf": "{install-type} == 'manual'",
      "elements": [
        {
          "type": "radiogroup",
          "name": "install-type",
          "title": {
            "default": "Which type of the install are you trying to make?",
            "nb": "Hvilken type installasjon prøver du å gjøre?"
          },
          "isRequired": true,
          "colCount": 1,
          "choices": [
            {
              "value": "production",
              "text": {
                "default": "Production - Install to a production licensed environment",
                "nb": "Produksjon – installere i et produksjonslisensiert miljø"
              }
            },
            {
              "value": "non-production",
              "text": {
                "default": "Non production - Install to a development or test environment",
                "nb": "Ikke-produksjon – Installere i et utviklings- eller testmiljø"
              }
            }
          ]
        },
        {
          "type": "radiogroup",
          "name": "method",
          "title": {
            "default": "Which of the following install method do you want to try?",
            "nb": "Hvilken av følgende installasjonsmetoder vil du prøve?"
          },
          "isRequired": true,
          "colCount": 1,
          "choices": [
            {
              "value": "development",
              "text": {
                "default": "Install to a Power Platform development environment",
                "nb": "Installere i et Power Platform utviklingsmiljø"
              }
            },
            {
              "value": "shared",
              "text": {
                "default": "Install to a shared Power Platform environment",
                "nb": "Installere i et delt Power Platform-miljø"
              }
            },
            {
              "value": "trial-30",
              "text": {
                "default": "Install into 30 day trial Power Platform environment",
                "nb": "Installer i 30 dagers prøveversjon Power Platform miljø"
              }
            }
          ]
        },
        {
          "type": "checkbox",
          "name": "components",
          "title": {
            "default": "Which of the following components did you want to install?",
            "nb": "Hvilke av følgende komponenter ønsket du å installere?"
          },
          "isRequired": true,
          "colCount": 1,
          "choices": [
            {
              "value": "main",
              "text": {
                "default": "The **main solution** that can be used to setup Automation Projects and expected ROI",
                "nb": "Den **Hovedløsning** som kan brukes til å sette opp automatiseringsprosjekter og forventet avkastning"
              }
            },
            {
              "value": "dashboard",
              "text": {
                "default": "A **Power BI dashboard** that reads data from the main environment to display ROI, complexity and monitor solutions",
                "nb": "En **Power BI-instrumentbord** som leser data fra hovedmiljøet for å vise avkastning, kompleksitet og overvåkingsløsninger"
              }
            },
            {
              "value": "satellite",
              "text": {
                "default": "Install **satellite solution** to monitor deployed Power Automate Desktop solution",
                "nb": "Installere **satellitt løsning** for å overvåke distribuert Power Automate Desktop-løsning"
              }
            }
          ]
        },
        {
          "type": "html",
          "html": {
            "default": "If you are not sure of these components, the <a href='https://learn.microsoft.com/power-automate/guidance/automation-kit/overview/introduction' target='_blank'>Automation Kit Introduction</a> can help provide information",
            "nb": "Hvis du ikke er sikker på disse komponentene, vises <a href='https://learn.microsoft.com/power-automate/guidance/automation-kit/overview/introduction' target='_blank'>Introduksjon av automatiseringssett</a> kan bidra til å gi informasjon"
          }
        },
        {
          "type": "html",
          "html": {
            "default": "NOTE: The setup of the satellite solution will require addition <b>Microsoft Azure</b> resources to complete the setup",
            "nb": "MERK: Oppsettet av satellittløsningen vil kreve tillegg <b>Microsoft Azure</b> ressurser for å fullføre installasjonen"
          },
          "visibleIf": "contains({components}, 'satellite')"
        },
        {
          "type": "checkbox",
          "name": "developmentChecks",
          "title": {
            "default": "Which of the following apply?",
            "nb": "Hvilket av følgende gjelder?"
          },
          "isRequired": true,
          "colCount": 1,
          "choices": [
            {
              "value": "dev-lic",
              "text": {
                "default": "I want to assign Development license",
                "nb": "Jeg vil tilordne utviklingslisens"
              }
            },
            {
              "value": "dev-env",
              "text": {
                "default": "I have been assigned a Development environment",
                "nb": "Jeg har fått tildelt et utviklingsmiljø"
              }
            }
          ],
          "visibleIf": "{method} = 'development'"
        },
        {
          "type": "checkbox",
          "name": "devLicenseEnv",
          "title": {
            "default": "Developer License Environment - Select the items below that apply",
            "nb": "Lisensmiljø for utviklere – Velg elementene nedenfor som gjelder"
          },
          "isRequired": true,
          "colCount": 1,
          "choices": [
            {
              "value": "azure-portal",
              "text": {
                "default": "Can open the <a href='https://portal.azure.com/#view/Microsoft_AAD_UsersAndTenants/UserManagementMenuBlade/~/AllUsers' target='_blank'>Azure Portal - Users</a>",
                "nb": "Kan åpne <a href='https://portal.azure.com/#view/Microsoft_AAD_UsersAndTenants/UserManagementMenuBlade/~/AllUsers' target='_blank'>Azure Portal - Brukere</a>"
              }
            },
            {
              "value": "Can search for your user name",
              "text": {
                "default": "Can search for your user name",
                "nb": "Kan søke etter brukernavnet ditt"
              }
            },
            {
              "value": "Can open user record",
              "text": {
                "default": "Can open user record",
                "nb": "Kan åpne brukeroppføring"
              }
            },
            {
              "value": "Can select 'Licenses' for your user",
              "text": {
                "default": "Can select 'Licenses' for your user",
                "nb": "Kan velge \"Lisenser\" for brukeren din"
              }
            },
            {
              "value": "dev-lic",
              "text": {
                "default": "Can verify that find 'Microsoft Power Apps for Developer' assigned",
                "nb": "Kan kontrollere at finner 'Microsoft Power Apps for Developer' tilordnet"
              }
            },
            {
              "value": "Can visit <a href='https://make.powerapps.com' target='_blank'>https://make.powerapps.com</a>",
              "text": {
                "default": "Can visit <a href='https://make.powerapps.com' target='_blank'>https://make.powerapps.com</a>",
                "nb": "Kan besøke <a href='https://make.powerapps.com' target='_blank'>https://make.powerapps.com</a>"
              }
            },
            {
              "value": "dev-created",
              "text": {
                "default": "Development environment created",
                "nb": "Utviklingsmiljø opprettet"
              }
            },
            {
              "value": "unable-to-complete",
              "text": {
                "default": "Unable to complete **other** steps",
                "nb": "Kan ikke fullføre **annen** trinn"
              }
            }
          ],
          "visibleIf": "{method} = 'development' and contains({developmentChecks},'dev-lic')"
        },
        {
          "type": "html",
          "html": {
            "default": "🚫 It looks like you have hit a road block with a developer license. Check if getting a developer or shared environment assigned to you. If this is not option, consider setting up a 30 day trial.",
            "nb": "🚫 Det ser ut til at du har truffet en veisperring med en utviklerlisens. Sjekk om du får en utvikler eller et delt miljø tilordnet til deg. Hvis dette ikke er et alternativ, bør du vurdere å konfigurere en 30-dagers prøveversjon."
          },
          "visibleIf": "{method} = 'development' and contains({devLicenseEnv}, 'unable-to-complete')"
        },
        {
          "type": "checkbox",
          "name": "devEnvironmentAssigned",
          "title": {
            "default": "Developer Assigned Environment - Select the items below that have been done",
            "nb": "Utviklertilordnet miljø – Velg elementene nedenfor som er gjort"
          },
          "isRequired": true,
          "colCount": 1,
          "choices": [
            {
              "value": "open-envs",
              "text": {
                "default": "Can open the <a href='https://admin.powerplatform.microsoft.com/environments' target='_blank'>Environments</a>",
                "nb": "Kan åpne <a href='https://admin.powerplatform.microsoft.com/environments' target='_blank'>Miljøer</a>"
              }
            },
            {
              "value": "dev-created",
              "text": {
                "default": "Can verify environment with Type 'Developer' exists",
                "nb": "Kan verifisere miljø med Type 'Utvikler' eksisterer"
              }
            },
            {
              "value": "unable-to-complete",
              "text": {
                "default": "Unable to complete all **other** steps",
                "nb": "Kan ikke fullføre alle **annen** trinn"
              }
            }
          ],
          "visibleIf": "{method} = 'development' and contains({developmentChecks},'dev-env')"
        },
        {
          "type": "html",
          "html": {
            "default": "🚫 It looks like you have hit a road block with a developer environment. Check if getting a developer license or a shared environment assigned are options in your organization. If not consider setting up a 30 day trial with a Non Production installation",
            "nb": "🚫 Det ser ut til at du har truffet en veisperring med et utviklermiljø. Kontroller om det å få en utviklerlisens eller et delt miljø tilordnet er alternativer i organisasjonen. Hvis ikke, bør du vurdere å sette opp en 30-dagers prøveversjon med en ikke-produksjonsinstallasjon"
          },
          "visibleIf": "{method} = 'development' and contains({devEnvironmentAssigned}, 'unable-to-complete')"
        },
        {
          "type": "checkbox",
          "name": "trial-setup",
          "title": {
            "default": "Trial Environment - Select the items below that have been done",
            "nb": "Prøvemiljø – Velg elementene nedenfor som er gjort"
          },
          "isRequired": true,
          "colCount": 1,
          "choices": [
            {
              "value": "Start a <a href='https://dynamics.microsoft.com/en-us/dynamics-365-free-trial/' target='_blank'>Dynamics 365 free trial</a>",
              "text": {
                "default": "Start a <a href='https://dynamics.microsoft.com/en-us/dynamics-365-free-trial/' target='_blank'>Dynamics 365 free trial</a>",
                "nb": "Start en <a href='https://dynamics.microsoft.com/en-us/dynamics-365-free-trial/' target='_blank'>Gratis prøveversjon av Dynamics 365</a>"
              }
            },
            {
              "value": "Login as free **Dynamics trial admin** created above and sign up for <a href='https://www.microsoft.com/en-gb/microsoft-365/try' target='_blank'>Try Microsoft 365 for free</a>",
              "text": {
                "default": "Login as free **Dynamics trial admin** created above and sign up for <a href='https://www.microsoft.com/en-gb/microsoft-365/try' target='_blank'>Try Microsoft 365 for free</a>",
                "nb": "Logg inn som gratis **Administrator for Dynamics-prøveversjon** opprettet ovenfor og registrer deg for <a href='https://www.microsoft.com/en-gb/microsoft-365/try' target='_blank'>Prøv Microsoft 365 gratis</a>"
              }
            },
            {
              "value": "As your **Dynamics trial admin** sign up for the <a href='https://powerapps.microsoft.com/en-us/developerplan/' target='_blank'>Power Apps Developer Plan</a> to be able to create development environments to install **Main** or **Satellite** solutions",
              "text": {
                "default": "As your **Dynamics trial admin** sign up for the <a href='https://powerapps.microsoft.com/en-us/developerplan/' target='_blank'>Power Apps Developer Plan</a> to be able to create development environments to install **Main** or **Satellite** solutions",
                "nb": "Som din **Administrator for Dynamics-prøveversjon** Registrer deg for <a href='https://powerapps.microsoft.com/en-us/developerplan/' target='_blank'>Utviklerplan for Power Apps</a> for å kunne skape utviklingsmiljøer som skal installeres **Hoved** eller **Satellitt** Løsninger"
              }
            },
            {
              "value": "Assign 'Microsoft Power Apps for Developer' licenses to trial users in <a href='https://portal.office.com' target='_blank'>Office Portal</a> or <a href='https://portal.azure.com/#view/Microsoft_AAD_IAM/LicensesMenuBlade/~/Overview' target='_blank'>Azure Portal</a>",
              "text": {
                "default": "Assign 'Microsoft Power Apps for Developer' licenses to trial users in <a href='https://portal.office.com' target='_blank'>Office Portal</a> or <a href='https://portal.azure.com/#view/Microsoft_AAD_IAM/LicensesMenuBlade/~/Overview' target='_blank'>Azure Portal</a>",
                "nb": "Tilordne lisenser for Microsoft Power Apps for Developer til prøvebrukere i <a href='https://portal.office.com' target='_blank'>Office-portalen</a> eller <a href='https://portal.azure.com/#view/Microsoft_AAD_IAM/LicensesMenuBlade/~/Overview' target='_blank'>Azure Portal</a>"
              }
            },
            {
              "value": "unable-to-complete",
              "text": {
                "default": "Unable to complete **other** steps",
                "nb": "Kan ikke fullføre **annen** trinn"
              }
            }
          ],
          "visibleIf": "{method} = 'trial-30'"
        },
        {
          "type": "html",
          "html": {
            "default": "🚫 It looks like you have hit a road block with a trial setup. Check if you can get a developer or shared environment assigned within you organization.",
            "nb": "🚫 Det ser ut til at du har truffet en veisperring med et prøveoppsett. Sjekk om du kan få tilordnet et utviklermiljø eller delt miljø i organisasjonen."
          },
          "visibleIf": "{method} = 'trial-30' and contains({trial-setup}, 'unable-to-complete')"
        },
        {
          "type": "comment",
          "name": "trial-setup-more-information",
          "title": {
            "default": "Would you like to provide more information on what problems you encountered?",
            "nb": "Vil du gi mer informasjon om hvilke problemer du opplevde?"
          },
          "visibleIf": "{method} = 'trial-30' and contains({trial-setup}, 'unable-to-complete')"
        },
        {
          "type": "checkbox",
          "name": "environmentSteps",
          "title": {
            "default": "Environment Setup - Select the items below that apply",
            "nb": "Miljøoppsett – Velg elementene nedenfor som gjelder"
          },
          "isRequired": true,
          "colCount": 1,
          "choices": [
            {
              "value": "admin-rights",
              "text": {
                "default": "I have environment administrator rights",
                "nb": "Jeg har rettigheter som miljøadministrator"
              },
              "visibleIf": "({method} = 'shared')"
            },
            {
              "value": "no-admin",
              "text": {
                "default": "I DO NOT have environment administrator rights",
                "nb": "Jeg har ikke rettigheter som miljøadministrator"
              },
              "visibleIf": "({method} = 'shared')"
            },
            {
              "value": "code-components",
              "text": {
                "default": "I have (or an environment administrator) has enabled code components in the environment using <a href='https://learn.microsoft.com/power-automate/guidance/automation-kit/setup/prerequisites#enable-code-components' target='_blank'>Enable code components</a> learn information",
                "nb": "Jeg har (eller en miljøadministrator) aktivert kodekomponenter i miljøet ved hjelp av <a href='https://learn.microsoft.com/power-automate/guidance/automation-kit/setup/prerequisites#enable-code-components' target='_blank'>Aktivere kodekomponenter</a> Lær informasjon"
              }
            },
            {
              "value": "creator-kit",
              "text": {
                "default": "I have (or an environment administrator) has installed the creator kit using <a href=' https://learn.microsoft.com/power-automate/guidance/automation-kit/setup/main#creator-kit-import' target='_blank'>Creator Kit Import</a> learn information",
                "nb": "Jeg har (eller en miljøadministrator) har installert skapersettet ved hjelp av <a href=' https://learn.microsoft.com/power-automate/guidance/automation-kit/setup/main#creator-kit-import' target='_blank'>Import av skapersett</a> Lær informasjon"
              }
            },
            {
              "value": "main-creator-kit",
              "text": {
                "default": "I have setup creator kit for **main** environment",
                "nb": "Jeg har setup creator kit for **hoved** miljø"
              },
              "visibleIf": "contains({components},'main')"
            },
            {
              "value": "main-creator-kit",
              "text": {
                "default": "I have setup creator kit for EACH **satellite** environment",
                "nb": "Jeg har setup creator kit for hver **satellitt** miljø"
              },
              "visibleIf": "contains({components},'satellite')"
            },
            {
              "value": "unable-to-complete",
              "text": {
                "default": "Unable to complete **other** steps",
                "nb": "Kan ikke fullføre **annen** trinn"
              }
            }
          ]
        },
        {
          "type": "html",
          "html": {
            "default": "🚫 It looks like you have hit a road block with a environment setup. Look to share <a href='https://aka.ms/automation-kit-learn' target='_blank'>Learn Content</a> with your Center of Excellence team. If this is not an option you could consider setting up a 30 day trial. You can also look to create a issue at <a href='https://aka.ms/ak4pp-issues' target='_blank'>https://aka.ms/ak4pp-issues</a>.",
            "nb": "🚫 Det ser ut til at du har truffet en veisperring med et miljøoppsett. Se etter å dele <a href='https://aka.ms/automation-kit-learn' target='_blank'>Lær innhold</a> med Center of Excellence-teamet ditt. Hvis dette ikke er et alternativ, kan du vurdere å sette opp en 30-dagers prøveversjon. Du kan også se for å opprette et problem på <a href='https://aka.ms/ak4pp-issues' target='_blank'>https://aka.ms/ak4pp-issues</a>."
          },
          "visibleIf": "contains({environmentSteps},'unable-to-complete')"
        },
        {
          "type": "checkbox",
          "name": "mainSetup",
          "title": {
            "default": "Main Solution Environment - Select the items below that have been done",
            "nb": "Hovedløsningsmiljø – Velg elementene nedenfor som er utført"
          },
          "isRequired": true,
          "colCount": 1,
          "choices": [
            {
              "value": "admin-rights",
              "text": {
                "default": "I have admin rights the shared environment",
                "nb": "Jeg har administratorrettigheter for det delte miljøet"
              },
              "visibleIf": "({method} = 'shared')"
            },
            {
              "value": "no-admin",
              "text": {
                "default": "I DO NOT have environment administrator rights",
                "nb": "Jeg har ikke rettigheter som miljøadministrator"
              },
              "visibleIf": "({method} = 'shared')"
            },
            {
              "value": "code-components",
              "text": {
                "default": "I have (or an environment administrator) has enabled code components in the environment using <a href='https://learn.microsoft.com/power-automate/guidance/automation-kit/setup/prerequisites#enable-code-components' target='_blank'>Enable code components</a> learn information",
                "nb": "Jeg har (eller en miljøadministrator) aktivert kodekomponenter i miljøet ved hjelp av <a href='https://learn.microsoft.com/power-automate/guidance/automation-kit/setup/prerequisites#enable-code-components' target='_blank'>Aktivere kodekomponenter</a> Lær informasjon"
              },
              "visibleIf": "({method} = 'shared')"
            },
            {
              "value": "creator-kit",
              "text": {
                "default": "I have imported the creator kit <a href=' https://learn.microsoft.com/power-automate/guidance/automation-kit/setup/main#creator-kit-import' target='_blank'>Creator kit import</a> using the learn steps into each satellite environment",
                "nb": "Jeg har importert skapersettet <a href=' https://learn.microsoft.com/power-automate/guidance/automation-kit/setup/main#creator-kit-import' target='_blank'>Import av skapersett</a> Bruke læringstrinnene i hvert satellittmiljø"
              }
            },
            {
              "value": "cli-install",
              "text": {
                "default": "I have completed the automated command line install in <a href='/get-started/setup' target='_blank'>Setup</a>",
                "nb": "Jeg har fullført den automatiserte kommandolinjeinstallasjonen i <a href='/get-started/setup' target='_blank'>Installasjonsprogrammet</a>"
              }
            },
            {
              "value": "solution-import",
              "text": {
                "default": "I successfully imported the solution using the steps in <a href='https://learn.microsoft.com/power-automate/guidance/automation-kit/setup/main#import-the-main-solution-into-the-main-environment' target='_blank'>Learn</a>",
                "nb": "Jeg importerte løsningen ved hjelp av trinnene i <a href='https://learn.microsoft.com/power-automate/guidance/automation-kit/setup/main#import-the-main-solution-into-the-main-environment' target='_blank'>Lære</a>"
              }
            },
            {
              "value": "approvals",
              "text": {
                "default": "I successfully provisioned the approvals solution using the steps in <a href='https://learn.microsoft.com/power-automate/guidance/automation-kit/setup/main#provision-the-approvals-solution-optional' target='_blank'>Learn</a>",
                "nb": "Jeg klargjorde godkjenningsløsningen ved hjelp av trinnene i <a href='https://learn.microsoft.com/power-automate/guidance/automation-kit/setup/main#provision-the-approvals-solution-optional' target='_blank'>Lære</a>"
              }
            },
            {
              "value": "assign-security-roles",
              "text": {
                "default": "I successfully assigned the security roles using the steps in <a href='https://learn.microsoft.com/power-automate/guidance/automation-kit/setup/main#assign-security-roles' target='_blank'>Learn</a>",
                "nb": "Jeg tilordnet sikkerhetsrollene ved hjelp av trinnene i <a href='https://learn.microsoft.com/power-automate/guidance/automation-kit/setup/main#assign-security-roles' target='_blank'>Lære</a>"
              }
            },
            {
              "value": "sync-environments",
              "text": {
                "default": "I successfully sync the environments using the steps in <a href='https://learn.microsoft.com/power-automate/guidance/automation-kit/setup/main#sync-environments' target='_blank'>Learn</a>",
                "nb": "Jeg synkroniserer miljøene ved hjelp av trinnene i <a href='https://learn.microsoft.com/power-automate/guidance/automation-kit/setup/main#sync-environments' target='_blank'>Lære</a>"
              }
            },
            {
              "value": "desktop-flow-actions",
              "text": {
                "default": "I successfully imported the desktop flow actions in <a href='https://learn.microsoft.com/power-automate/guidance/automation-kit/setup/main#import-the-desktop-flow-actions-csv' target='_blank'>Learn</a>",
                "nb": "Jeg importerte skrivebordsflythandlingene i <a href='https://learn.microsoft.com/power-automate/guidance/automation-kit/setup/main#import-the-desktop-flow-actions-csv' target='_blank'>Lære</a>"
              }
            },
            {
              "value": "configured-kit",
              "text": {
                "default": "I successfully used the automation kit steps in <a href='https://learn.microsoft.com/power-automate/guidance/automation-kit/use-automation-kit' target='_blank'>Use the Automation Kit</a>",
                "nb": "Jeg har brukt automatiseringssetttrinnene i <a href='https://learn.microsoft.com/power-automate/guidance/automation-kit/use-automation-kit' target='_blank'>Bruk automatiseringssettet</a>"
              }
            },
            {
              "value": "unable-to-complete",
              "text": {
                "default": "Unable to complete **other** steps",
                "nb": "Kan ikke fullføre **annen** trinn"
              }
            }
          ],
          "visibleIf": "contains({components},'main')"
        },
        {
          "type": "html",
          "html": {
            "default": "🚫 It looks like you have hit a road block with a main solution setup. Look to share <a href='https://aka.ms/automation-kit-learn' target='_blank'>Learn Content</a> with your Center of Excellence team. You can also look to create a issue at <a href='https://aka.ms/ak4pp-issues' target='_blank'>https://aka.ms/ak4pp-issues</a>.",
            "nb": "🚫 Det ser ut til at du har truffet en veisperring med et hovedløsningsoppsett. Se etter å dele <a href='https://aka.ms/automation-kit-learn' target='_blank'>Lær innhold</a> med Center of Excellence-teamet ditt. Du kan også se for å opprette et problem på <a href='https://aka.ms/ak4pp-issues' target='_blank'>https://aka.ms/ak4pp-issues</a>."
          },
          "visibleIf": "contains({mainSetup},'unable-to-complete')"
        },
        {
          "type": "comment",
          "name": "main-setup-more-information",
          "title": {
            "default": "Would you like to provide more information on what problems you encountered?",
            "nb": "Vil du gi mer informasjon om hvilke problemer du opplevde?"
          },
          "visibleIf": "contains({mainSetup},'unable-to-complete')"
        },
        {
          "type": "checkbox",
          "name": "dashboardSetup",
          "title": {
            "default": "Dashboard setup - Select the items below that have been done",
            "nb": "Dashbordoppsett - Velg elementene nedenfor som er gjort"
          },
          "isRequired": true,
          "colCount": 1,
          "choices": [
            {
              "value": "powerbi-install",
              "text": {
                "default": "Review the Power BI desktop install instructions at <a href='/get-started/install-powerbi-dashboard' target='_blank'>Setup Automation Kit Power BI dashboard</a>.",
                "nb": "Se gjennom installasjonsinstruksjonene for Power BI Desktop på <a href='/get-started/install-powerbi-dashboard' target='_blank'>Oppsett av automatiseringssett Power BI-instrumentbord</a>."
              }
            },
            {
              "value": "unable-to-complete",
              "text": {
                "default": "Unable to complete **other** steps",
                "nb": "Kan ikke fullføre **annen** trinn"
              }
            }
          ],
          "visibleIf": "contains({components},'dashboard')"
        },
        {
          "type": "html",
          "html": {
            "default": "🚫 It looks like you have hit a road block with the Power BI dashboard setup. You could look at creating an issue at <a href='https://aka.ms/ak4pp-issues' target='_blank'>https://aka.ms/ak4pp-issues</a>.",
            "nb": "🚫 Det ser ut til at du har truffet en veisperring med oppsettet av Power BI-instrumentbordet. Du kan se på å opprette et problem på <a href='https://aka.ms/ak4pp-issues' target='_blank'>https://aka.ms/ak4pp-issues</a>."
          },
          "visibleIf": "contains({components},'dashboard') and contains({dashboardSetup},'unable-to-complete')"
        },
        {
          "type": "comment",
          "name": "dashboard-setup-more-information",
          "title": {
            "default": "Would you like to provide more information on what problems you encountered?",
            "nb": "Vil du gi mer informasjon om hvilke problemer du opplevde?"
          },
          "visibleIf": "contains({mainSetup},'unable-to-complete')"
        },
        {
          "type": "checkbox",
          "name": "satelliteSetup",
          "title": {
            "default": "Satellite Solution Environment - Select the items below that have been done",
            "nb": "Satellittløsningsmiljø – Velg elementene nedenfor som er gjort"
          },
          "isRequired": true,
          "colCount": 1,
          "choices": [
            {
              "value": "admin-rights",
              "text": {
                "default": "I have admin rights the shared environment",
                "nb": "Jeg har administratorrettigheter for det delte miljøet"
              },
              "visibleIf": "({method} = 'shared')"
            },
            {
              "value": "no-admin",
              "text": {
                "default": "I DO NOT have environment administrator rights",
                "nb": "Jeg har ikke rettigheter som miljøadministrator"
              },
              "visibleIf": "({method} = 'shared')"
            },
            {
              "value": "code-components",
              "text": {
                "default": "I have (or an environment administrator) has enabled code components in the environment using <a href='https://learn.microsoft.com/power-automate/guidance/automation-kit/setup/prerequisites#enable-code-components' target='_blank'>Enable code components</a> learn information",
                "nb": "Jeg har (eller en miljøadministrator) aktivert kodekomponenter i miljøet ved hjelp av <a href='https://learn.microsoft.com/power-automate/guidance/automation-kit/setup/prerequisites#enable-code-components' target='_blank'>Aktivere kodekomponenter</a> Lær informasjon"
              },
              "visibleIf": "({method} = 'shared')"
            },
            {
              "value": "creator-kit",
              "text": {
                "default": "I have imported the creator kit <a href=' https://learn.microsoft.com/power-automate/guidance/automation-kit/setup/main#creator-kit-import' target='_blank'>Creator kit import</a> using the learn steps into each satellite environment",
                "nb": "Jeg har importert skapersettet <a href=' https://learn.microsoft.com/power-automate/guidance/automation-kit/setup/main#creator-kit-import' target='_blank'>Import av skapersett</a> Bruke læringstrinnene i hvert satellittmiljø"
              }
            },
            {
              "value": "aad",
              "text": {
                "default": "I created the Azure Active Directory application and secret from <a href='https://learn.microsoft.com/power-automate/guidance/automation-kit/setup/satellite#create-an-azure-ad-app-registration-to-connect-to-dataverse-web-api' target='_blank'>Learn</a>",
                "nb": "Jeg opprettet Azure Active Directory-programmet og hemmeligheten fra <a href='https://learn.microsoft.com/power-automate/guidance/automation-kit/setup/satellite#create-an-azure-ad-app-registration-to-connect-to-dataverse-web-api' target='_blank'>Lære</a>"
              }
            },
            {
              "value": "aad-user-setup",
              "text": {
                "default": "I have setup the application user in the satellite environment <a href='https://learn.microsoft.com/power-automate/guidance/automation-kit/setup/satellite#create-application-user-inside-dataverse-per-satellite-env' target='_blank'>Learn</a>",
                "nb": "Jeg har konfigurert programbrukeren i satellittmiljøet <a href='https://learn.microsoft.com/power-automate/guidance/automation-kit/setup/satellite#create-application-user-inside-dataverse-per-satellite-env' target='_blank'>Lære</a>"
              }
            },
            {
              "value": "cli-install",
              "text": {
                "default": "I have completed the automated command line install in <a href='/get-started/setup' target='_blank'>Setup</a>",
                "nb": "Jeg har fullført den automatiserte kommandolinjeinstallasjonen i <a href='/get-started/setup' target='_blank'>Installasjonsprogrammet</a>"
              }
            },
            {
              "value": "solution-import",
              "text": {
                "default": "I successfully imported the solution using the steps in <a href='https://learn.microsoft.com/power-automate/guidance/automation-kit/setup/satellite#import-the-satellite-solution-into-the-satellite-environment' target='_blank'>Learn</a>",
                "nb": "Jeg importerte løsningen ved hjelp av trinnene i <a href='https://learn.microsoft.com/power-automate/guidance/automation-kit/setup/satellite#import-the-satellite-solution-into-the-satellite-environment' target='_blank'>Lære</a>"
              }
            },
            {
              "value": "desktop-flow-actions",
              "text": {
                "default": "I successfully imported the desktop flow actions in <a href='https://learn.microsoft.com/en-us/power-automate/guidance/automation-kit/setup/satellite#import-the-desktop-flow-actions-csv' target='_blank'>Learn</a>",
                "nb": "Jeg importerte skrivebordsflythandlingene i <a href='https://learn.microsoft.com/en-us/power-automate/guidance/automation-kit/setup/satellite#import-the-desktop-flow-actions-csv' target='_blank'>Lære</a>"
              }
            },
            {
              "value": "setup-environment-variables",
              "text": {
                "default": "I have setup environment as described in <a href='https://learn.microsoft.com/power-automate/guidance/automation-kit/setup/environment-variables' target='_blank'>Environment variables</a>",
                "nb": "Jeg har oppsett miljø som beskrevet i <a href='https://learn.microsoft.com/power-automate/guidance/automation-kit/setup/environment-variables' target='_blank'>Miljøvariabler</a>"
              }
            },
            {
              "value": "unable-to-complete",
              "text": {
                "default": "Unable to complete **other** steps",
                "nb": "Kan ikke fullføre **annen** trinn"
              }
            }
          ],
          "visibleIf": "contains({components},'satellite')"
        },
        {
          "type": "html",
          "html": {
            "default": "🚫 It looks like you have hit a road block with a satellite setup. Look to share <a href='https://aka.ms/automation-kit-learn' target='_blank'>Learn Content</a> with your Center of Excellence team. You can also look to create a issue at <a href='https://aka.ms/ak4pp-issues' target='_blank'>https://aka.ms/ak4pp-issues</a>.",
            "nb": "🚫 Det ser ut til at du har truffet en veisperring med et satellittoppsett. Se etter å dele <a href='https://aka.ms/automation-kit-learn' target='_blank'>Lær innhold</a> med Center of Excellence-teamet ditt. Du kan også se for å opprette et problem på <a href='https://aka.ms/ak4pp-issues' target='_blank'>https://aka.ms/ak4pp-issues</a>."
          },
          "visibleIf": "contains({components},'satellite') and contains({satelliteSetup},'unable-to-complete')"
        },
        {
          "type": "comment",
          "name": "satellite-setup-more-information",
          "title": {
            "default": "Would you like to provide more information on what problems you encountered?",
            "nb": "Vil du gi mer informasjon om hvilke problemer du opplevde?"
          },
          "visibleIf": "contains({components},'satellite') and contains({satelliteSetup},'unable-to-complete')"
        }
      ]
    },
    {
      "elements": [
        {
          "type": "boolean",
          "name": "send-results",
          "label": {
            "default": "Do you want to send the results of the your install check list so that the Core Automation Kit team can learn what worked?",
            "nb": "Vil du sende resultatene av sjekklisten for installering, slik at Core Automation Kit-teamet kan finne ut hva som fungerte?"
          },
          "isRequired": true
        },
        {
          "type": "html",
          "visibleIf": "{send-results} = false",
          "html": {
            "default": "We hope this checklist helped you with the non production install",
            "nb": "Vi håper denne sjekklisten hjalp deg med ikke-produksjonsinstallasjonen"
          }
        },
        {
          "type": "html",
          "visibleIf": "{send-results} = true",
          "html": {
            "default": "We look forward to getting your feedback. As a core Automation Kit team we use the feedback to improving our getting started guidance",
            "nb": "Vi ser frem til å få din tilbakemelding. Som et kjerneteam for automatiseringssett bruker vi tilbakemeldingene til å forbedre veiledningen for å komme i gang"
          }
        },
        {
          "type": "comment",
          "name": "other-feedback",
          "title": {
            "default": "Did you have any other feedback?",
            "nb": "Har du noen andre tilbakemeldinger?"
          },
          "visibleIf": "{send-results} = true"
        },
        {
          "type": "feedback-task",
          "name": "send-results-feedback",
          "title": {
            "default": "Send your feedback now?",
            "nb": "Send tilbakemelding nå?"
          },
          "destination": "https://aka.ms/ak4pp-feedback2",
          "visibleIf": "{send-results} = true"
        },
        {
          "type": "html",
          "visibleIf": "{send-results-status.length} > 0",
          "html": {
            "default": "Status: {send-results-status}",
            "nb": "Status: "
          }
        }
      ]
    }
  ]
}