{
  "triggers": [
    {
      "type": "setvalue",
      "expression": "contains({roles},['All', 'Center Of Excellence']) = false",
      "setToName": "non-technical",
      "setValue": true
    },
    {
      "type": "setvalue",
      "expression": "{send-results} = true",
      "setToName": "code",
      "setValue": "Feedback-Get-Started-Checklist"
    }
  ],
  "pages": [
    {
      "name": "welcome",
      "elements": [
        {
          "type": "checkbox",
          "name": "roles",
          "title": {
            "default": "Which of the following role(s) are the best match for you?",
            "da": "Hvilke(n) af følgende roller, der passer bedst til dig?"
          },
          "isRequired": true,
          "colCount": 2,
          "choices": [
            {
              "value": "Goal Setter",
              "text": {
                "default": "Goal Setter",
                "da": "Målscorer"
              }
            },
            {
              "value": "Process Owner",
              "text": {
                "default": "Process Owner",
                "da": "Procesejer"
              }
            },
            {
              "value": "Reviewer",
              "text": {
                "default": "Reviewer",
                "da": "Reviewer"
              }
            },
            {
              "value": "Center Of Excellence",
              "text": {
                "default": "Center Of Excellence",
                "da": "Center Of Excellence"
              }
            },
            {
              "value": "Administrator",
              "text": {
                "default": "Administrator",
                "da": "Administrator"
              }
            },
            {
              "value": "Compliance",
              "text": {
                "default": "Compliance",
                "da": "Overholdelse"
              }
            },
            {
              "value": "Information Security",
              "text": {
                "default": "Information Security",
                "da": "Informationssikkerhed"
              }
            },
            {
              "value": "Audit",
              "text": {
                "default": "Audit",
                "da": "Revision"
              }
            },
            {
              "value": "All",
              "text": {
                "default": "All",
                "da": "Al"
              }
            }
          ]
        },
        {
          "name": "roleNotSure",
          "type": "boolean",
          "title": {
            "default": "Not sure of roles, tell me more about selected items",
            "da": "Ikke sikker på roller, fortæl mig mere om udvalgte emner"
          },
          "defaultValue": false
        },
        {
          "type": "html",
          "html": {
            "default": "<b>Goal Setter</b> - This could be a Corporate or Department decision maker role <a href='https://learn.microsoft.com/power-automate/guidance/automation-kit/overview/automation-coe-strategy#automation-lifecycle' target='_blank'>Learn More</a>",
            "da": "<b>Målscorer</b> - Det kan være en beslutningstagerrolle i virksomheden eller afdelingen. <a href='https://learn.microsoft.com/power-automate/guidance/automation-kit/overview/automation-coe-strategy#automation-lifecycle' target='_blank'>Lær mere</a>"
          },
          "visibleIf": "({roleNotSure} = true) and contains({roles},['Goal Setter','All'])"
        },
        {
          "type": "html",
          "html": {
            "default": "<b>Process Owner</b> - Creates the Automation Projects in the system <a href='https://learn.microsoft.com/power-automate/guidance/automation-kit/overview/automation-coe-strategy#automation-lifecycle' target='_blank'>Learn More</a>",
            "da": "<b>Procesejer</b> - Opretter automatiseringsprojekterne i systemet <a href='https://learn.microsoft.com/power-automate/guidance/automation-kit/overview/automation-coe-strategy#automation-lifecycle' target='_blank'>Lær mere</a>"
          },
          "visibleIf": "({roleNotSure} = true) and contains({roles},['Process Owner','All'])"
        },
        {
          "type": "html",
          "html": {
            "default": "<b>Reviewer</b> - Validates idea to approve that the idea should be implemented and is justifiable <a href='https://learn.microsoft.com/power-automate/guidance/automation-kit/overview/automation-coe-strategy#automation-lifecycle' target='_blank'>Learn More</a>",
            "da": "<b>Reviewer</b> - Validerer ideen til at godkende, at ideen skal implementeres og er forsvarlig <a href='https://learn.microsoft.com/power-automate/guidance/automation-kit/overview/automation-coe-strategy#automation-lifecycle' target='_blank'>Lær mere</a>"
          },
          "visibleIf": "({roleNotSure} = true) and contains({roles},['Reviewer','All'])"
        },
        {
          "type": "html",
          "html": {
            "default": "<b>Center Of Excellence</b> - Sets up and maps solution to a specific environment <a href='https://learn.microsoft.com/power-automate/guidance/automation-kit/overview/automation-coe-strategy#automation-lifecycle' target='_blank'>Learn More</a>",
            "da": "<b>Center Of Excellence</b> - Opsætning og kortlægning af løsning til et specifikt miljø <a href='https://learn.microsoft.com/power-automate/guidance/automation-kit/overview/automation-coe-strategy#automation-lifecycle' target='_blank'>Lær mere</a>"
          },
          "visibleIf": "({roleNotSure} = true) and contains({roles},['Center Of Excellence','All'])"
        },
        {
          "type": "html",
          "html": {
            "default": "<b>Administrator</b> - May set Power Platform environment management and creation of Data Loss Prevention (DLP) policies that need to be put in place for the organization to scale <a href='https://learn.microsoft.com/power-automate/guidance/automation-kit/overview/automation-coe-strategy#power-platform-and-microsoft-365-coes' target='_blank'>Learn More</a>",
            "da": "<b>Administrator</b> - Kan fastsætte Power Platform miljøstyring og oprettelse af politikker for forebyggelse af datatab (DLP), der skal indføres for at organisationen kan skaleres <a href='https://learn.microsoft.com/power-automate/guidance/automation-kit/overview/automation-coe-strategy#power-platform-and-microsoft-365-coes' target='_blank'>Lær mere</a>"
          },
          "visibleIf": "({roleNotSure} = true) and contains({roles},['Administrator','All'])"
        },
        {
          "type": "html",
          "html": {
            "default": "<b>Compliance, Information Security, Audit</b> - Set the corporate rules, regulations, cyber-security, data privacy, and auditing requirements as part of <a href='https://learn.microsoft.com/power-automate/guidance/automation-kit/overview/automation-coe-strategy#corporate-automation-strategy' target='_blank'>Corporate automation strategy</a>",
            "da": "<b>Overholdelse, informationssikkerhed, revision</b> - Sæt virksomhedens regler, forskrifter, cybersikkerhed, databeskyttelse og revisionskrav som en del af <a href='https://learn.microsoft.com/power-automate/guidance/automation-kit/overview/automation-coe-strategy#corporate-automation-strategy' target='_blank'>Strategi for automatisering af virksomheder</a>"
          },
          "visibleIf": "({roleNotSure} = true) and contains({roles},['Compliance', 'Information Security', 'Audit','All'])"
        },
        {
          "type": "radiogroup",
          "name": "checkInstalled",
          "title": {
            "default": "Does you organization have the Automation Kit for Power Platform installed?",
            "da": "Har din organisation Automation Kit til Power Platform installeret?"
          },
          "isRequired": true,
          "colCount": 1,
          "choices": [
            {
              "value": "Yes",
              "text": {
                "default": "Yes",
                "da": "Ja"
              }
            },
            {
              "value": "No",
              "text": {
                "default": "No",
                "da": "Nej"
              }
            },
            {
              "value": "Not Sure",
              "text": {
                "default": "Not Sure",
                "da": "Ikke sikker"
              }
            }
          ],
          "visibleIf": "{roles} notempty"
        },
        {
          "type": "html",
          "html": {
            "default": "Great you can review the <a href='https://learn.microsoft.com/power-automate/guidance/automation-kit/use-automation-kit' target='_blank'>Use the Automation Kit</a> for more information",
            "da": "Fantastisk du kan gennemgå <a href='https://learn.microsoft.com/power-automate/guidance/automation-kit/use-automation-kit' target='_blank'>Brug automatiseringssættet</a> Yderligere oplysninger"
          },
          "visibleIf": "{checkInstalled}='Yes'"
        },
        {
          "type": "checkbox",
          "name": "technicalNotInstalled",
          "title": {
            "default": "Ok the Automation Kit is not installed, what technical task do you need help with?",
            "da": "Ok automatiseringssættet er ikke installeret, hvilken teknisk opgave har du brug for hjælp til?"
          },
          "isRequired": true,
          "colCount": 4,
          "choices": [
            {
              "value": "Help with install",
              "text": {
                "default": "Help with install",
                "da": "Hjælp til installation"
              }
            },
            {
              "value": "Setup instructions",
              "text": {
                "default": "Setup instructions",
                "da": "Opsætning instruktioner"
              }
            },
            {
              "value": "Further support",
              "text": {
                "default": "Further support",
                "da": "Yderligere support"
              }
            }
          ],
          "visibleIf": "({checkInstalled}='No' or {checkInstalled}='Not Sure') and contains({roles},['All', 'Center Of Excellence']) = true"
        },
        {
          "type": "checkbox",
          "name": "otherNotInstalled",
          "title": {
            "default": "Ok the Automation Kit is not installed, what do you need help with?",
            "da": "Ok automatiseringssættet er ikke installeret, hvad har du brug for hjælp til?"
          },
          "isRequired": true,
          "colCount": 4,
          "choices": [
            {
              "value": "Help with install",
              "text": {
                "default": "Help with install",
                "da": "Hjælp til installation"
              }
            },
            {
              "value": "Further support",
              "text": {
                "default": "Further support",
                "da": "Yderligere support"
              }
            }
          ],
          "visibleIf": "({checkInstalled}='No' or {checkInstalled}='Not Sure') and contains({roles},['All', 'Center Of Excellence']) = false"
        },
        {
          "type": "html",
          "html": {
            "default": "Start by reviewing the install <a href='https://learn.microsoft.com/power-automate/guidance/automation-kit/setup/prerequisites' target='_blank'>prerequisites</a> for more information",
            "da": "Start med at gennemgå installationen <a href='https://learn.microsoft.com/power-automate/guidance/automation-kit/setup/prerequisites' target='_blank'>Forudsætninger</a> Yderligere oplysninger"
          },
          "visibleIf": "contains({technicalNotInstalled},['Help with install', 'Setup instructions']) and contains({roles},['Center Of Excellence','All'])"
        },
        {
          "type": "html",
          "html": {
            "default": "Contact your Center of Excellence to install or check if Automation Kit is installed",
            "da": "Kontakt dit Center of Excellence for at installere eller kontrollere, om Automation Kit er installeret"
          },
          "visibleIf": "contains({otherNotInstalled},['Help with install'])"
        },
        {
          "type": "html",
          "html": {
            "default": "If you are looking to trial the Automation Kit to determine how it works and what value it can provide you could try a Non production install using the <a href='/get-started/install-checklist' target='_blank'>Install checklist</a> to rapidly get started",
            "da": "Hvis du ønsker at prøve automatiseringssættet for at bestemme, hvordan det fungerer, og hvilken værdi det kan give, kan du prøve en ikke-produktionsinstallation ved hjælp af <a href='/get-started/install-checklist' target='_blank'>Installer tjekliste</a> for hurtigt at komme i gang"
          },
          "visibleIf": "contains({otherNotInstalled},['Help with install'])"
        },
        {
          "type": "html",
          "html": {
            "default": "Review walkthrough install videos <a href='https://github.com/microsoft/powercat-automation-kit/blob/main/docs/walkthrough.md' target='_blank'>learn more</a>",
            "da": "Gennemgå gennemgangsinstallationsvideoer <a href='https://github.com/microsoft/powercat-automation-kit/blob/main/docs/walkthrough.md' target='_blank'>Lær mere</a>"
          },
          "visibleIf": "contains({technicalNotInstalled},['Help with install'])"
        },
        {
          "type": "html",
          "html": {
            "default": "Review our <a href='/support' target='_blank'>support</a> page for more information",
            "da": "Gennemgå vores <a href='/support' target='_blank'>støtte</a> side for mere information"
          },
          "visibleIf": "contains({technicalNotInstalled},['Further support']) or contains({otherNotInstalled},['Further support'])"
        },
        {
          "type": "checkbox",
          "name": "technical-Azure",
          "title": {
            "default": "Check the best Azure option(s) that apply to you",
            "da": "Tjek de(n) bedste Azure-løsning(er), der gælder for dig"
          },
          "isRequired": true,
          "colCount": 1,
          "choices": [
            {
              "value": "aad",
              "text": {
                "default": "I have rights to create Azure Active Directory application",
                "da": "Jeg har rettigheder til at oprette Azure Active Directory-programmet"
              }
            },
            {
              "value": "azure-create",
              "text": {
                "default": "I can create Azure resources (For example Azure Key Vault)",
                "da": "Jeg kan oprette Azure-ressourcer (f.eks. Azure Key Vault)"
              }
            },
            {
              "value": "azure-delegate",
              "text": {
                "default": "I need to work with Azure team to create resources for me",
                "da": "Jeg er nødt til at arbejde sammen med Azure-teamet for at skabe ressourcer til mig"
              }
            },
            {
              "value": "azure-contributor-aad",
              "text": {
                "default": "I have owner or contributor rights Azure Active Directory App",
                "da": "Jeg har ejer- eller bidragyderrettigheder til Azure Active Directory App"
              }
            },
            {
              "value": "azure-contributor-kv",
              "text": {
                "default": "I have owner or contributor rights Azure Key Vault",
                "da": "Jeg har ejer- eller bidragyderrettigheder til Azure Key Vault"
              }
            }
          ],
          "visibleIf": "({checkInstalled}='No' or {checkInstalled}='Not Sure') and contains({roles},['All', 'Center Of Excellence']) = true"
        },
        {
          "type": "html",
          "html": {
            "default": "Azure pre-requistes met",
            "da": "Azure pre-requistes met"
          },
          "visibleIf": "contains({technical-Azure},['azure-create','azure-contributor-aad','azure-contributor-kv','azure-delegate']) and contains({technical-Azure},['aad','azure-contributor-aad']) and contains({technical-Azure},['azure-create','azure-contributor-kv'])"
        },
        {
          "type": "html",
          "html": {
            "default": "Refer your Azure team to <a href='https://learn.microsoft.com/power-automate/guidance/automation-kit/setup/satellite' target='_blank'>Set up satellites</a> to create Azure App registration and Azure KeyVault Secrets",
            "da": "Henvis dit Azure-team til <a href='https://learn.microsoft.com/power-automate/guidance/automation-kit/setup/satellite' target='_blank'>Opsæt satellitter</a> for at oprette Azure App-registrering og Azure KeyVault-hemmeligheder"
          },
          "visibleIf": "contains({technical-Azure},['azure-delegate'])"
        },
        {
          "type": "checkbox",
          "name": "technical-O365",
          "title": {
            "default": "Check the best Office 365 option(s) that apply for you",
            "da": "Tjek de(n) bedste Office 365-indstilling(er), der gælder for dig"
          },
          "isRequired": true,
          "colCount": 1,
          "choices": [
            {
              "value": "lic",
              "text": {
                "default": "I have Office 365 E3 ",
                "da": "Jeg har Office 365 E3 "
              }
            },
            {
              "value": "not-sure",
              "text": {
                "default": "Not sure",
                "da": "Ikke sikker"
              }
            }
          ],
          "visibleIf": "({checkInstalled}='No' or {checkInstalled}='Not Sure') and contains({roles},['All', 'Center Of Excellence']) = true"
        },
        {
          "type": "html",
          "html": {
            "default": "Office 365 pre-requistes met",
            "da": "Office 365 pre-requistes mødtes"
          },
          "visibleIf": "contains({technical-O365},['lic'])"
        },
        {
          "type": "checkbox",
          "name": "technical-PP",
          "title": {
            "default": "Check the best Power Platform option(s) that apply for you",
            "da": "Tjek de bedste Power Platform muligheder, der gælder for dig"
          },
          "isRequired": true,
          "colCount": 1,
          "choices": [
            {
              "value": "pp-tenant-admin",
              "text": {
                "default": "I have Power Platform tenant admin rights",
                "da": "Jeg har administratorrettigheder Power Platform lejer"
              }
            },
            {
              "value": "pp-environment-admin",
              "text": {
                "default": "I have Power Platform environment admin right",
                "da": "Jeg har Power Platform miljøadministratorrettighed"
              }
            },
            {
              "value": "power-bi-pro",
              "text": {
                "default": "I have Power BI professional licenses available",
                "da": "Jeg har Power BI professional-licenser tilgængelige"
              }
            }
          ],
          "visibleIf": "({checkInstalled}='No' or {checkInstalled}='Not Sure') and contains({roles},['All', 'Center Of Excellence']) = true"
        },
        {
          "type": "html",
          "html": {
            "default": "Power Platform pre-requistes met",
            "da": "Power Platform præ-requistes mødtes"
          },
          "visibleIf": "contains({technical-PP},['pp-tenant-admin','pp-environment-admin']) and contains({technical-PP},['power-bi-pro'])"
        },
        {
          "type": "radiogroup",
          "name": "technical-ALM",
          "title": {
            "default": "Check the best ALM option(s) that apply for you for your Power Automation Desktop Deployments",
            "da": "Kontrollér de(n) bedste ALM-indstilling(er), der gælder for dig til dine Power Automation Desktop-installationer"
          },
          "isRequired": true,
          "colCount": 1,
          "choices": [
            {
              "value": "manual",
              "text": {
                "default": "We will manual import / export solutions between environments",
                "da": "Vi vil manuelt importere/eksportere løsninger mellem miljøer"
              }
            },
            {
              "value": "alm-setup",
              "text": {
                "default": "We need to setup ALM process for deployment",
                "da": "Vi er nødt til at konfigurere ALM-processen til implementering"
              }
            }
          ],
          "visibleIf": "({checkInstalled}='No' or {checkInstalled}='Not Sure') and contains({roles},['All', 'Center Of Excellence']) = true"
        },
        {
          "type": "html",
          "html": {
            "default": "Review <a href='https://learn.microsoft.com/power-platform/guidance/coe/almacceleratorpowerplatform-components' target='_blank'>ALM Accelerator</a> for ALM automation install and setup documentation",
            "da": "Anmeldelse <a href='https://learn.microsoft.com/power-platform/guidance/coe/almacceleratorpowerplatform-components' target='_blank'>ALM Accelerator</a> til dokumentation til installation og opsætning af ALM"
          },
          "visibleIf": "{technical-ALM} = 'alm-setup'"
        },
        {
          "type": "radiogroup",
          "name": "technical-data",
          "title": {
            "default": "Check the best data setup option(s) that apply",
            "da": "Tjek de(n) bedste dataopsætningsmulighed(er), der gælder"
          },
          "isRequired": true,
          "colCount": 1,
          "choices": [
            {
              "value": "manual",
              "text": {
                "default": "We will follow documents to setup and configure Automation Kit data",
                "da": "Vi følger dokumenter for at konfigurere og konfigurere Automation Kit-data"
              }
            },
            {
              "value": "import",
              "text": {
                "default": "We would like to import pre-packaged sample data sets",
                "da": "Vi vil gerne importere færdigpakkede eksempeldatasæt"
              }
            }
          ],
          "visibleIf": "({checkInstalled}='No' or {checkInstalled}='Not Sure') and contains({roles},['All', 'Center Of Excellence']) = true"
        },
        {
          "type": "html",
          "html": {
            "default": "Review <a href='https://learn.microsoft.com/power-automate/guidance/automation-kit/configure-automation-kit' target='_blank'>Configure automation kit</a> learning content",
            "da": "Anmeldelse <a href='https://learn.microsoft.com/power-automate/guidance/automation-kit/configure-automation-kit' target='_blank'>Konfigurer automatiseringssæt</a> Læringsindhold"
          },
          "visibleIf": "{technical-data} = 'manual'"
        },
        {
          "type": "html",
          "html": {
            "default": "Watch <a href='https://github.com/microsoft/powercat-automation-kit/issues/19' target='_blank'>Sample Import</a> issue for progress",
            "da": "Ur <a href='https://github.com/microsoft/powercat-automation-kit/issues/19' target='_blank'>Eksempel på import</a> spørgsmål for fremskridt"
          },
          "visibleIf": "{technical-data} = 'import'"
        },
        {
          "name": "haveQuestionsHelped",
          "type": "boolean",
          "title": {
            "default": "Have these questions helped?",
            "da": "Har disse spørgsmål hjulpet?"
          }
        },
        {
          "type": "html",
          "html": {
            "default": "Review our <a href='/frequently-asked-questions' target='_blank'>frequently asked questions</a> page for other common Question and Answers",
            "da": "Gennemgå vores <a href='/frequently-asked-questions' target='_blank'>Ofte stillede spørgsmål</a> side for andre almindelige spørgsmål og svar"
          },
          "visibleIf": "{haveQuestionsHelped}=False"
        },
        {
          "type": "html",
          "html": {
            "default": "Consider giving feedback below on how we can improve",
            "da": "Overvej at give feedback nedenfor om, hvordan vi kan forbedre os"
          },
          "visibleIf": "{haveQuestionsHelped}=False"
        },
        {
          "type": "html",
          "html": {
            "default": "Consider giving feedback below or create a <a href='https://github.com/microsoft/powercat-automation-kit/issues/new/choose' target='_blank'>New Kudos</a> or comment on an <a href='https://github.com/microsoft/powercat-automation-kit/issues?q=is%3Aopen+is%3Aissue+label%3Akudos' target='_blank'>existing Kudos</a> to provide feedback",
            "da": "Overvej at give feedback nedenfor eller oprette en <a href='https://github.com/microsoft/powercat-automation-kit/issues/new/choose' target='_blank'>Ny ros</a> eller kommenter en <a href='https://github.com/microsoft/powercat-automation-kit/issues?q=is%3Aopen+is%3Aissue+label%3Akudos' target='_blank'>eksisterende Kudos</a> at give feedback"
          },
          "visibleIf": "{haveQuestionsHelped}=True"
        },
        {
          "type": "boolean",
          "name": "send-results",
          "label": {
            "default": "Do you want to send the results of the your check list so that the Core Automation Kit team can gather your feedback to improve the process?",
            "da": "Vil du sende resultaterne af din tjekliste, så Core Automation Kit-teamet kan indsamle din feedback for at forbedre processen?"
          },
          "isRequired": true
        },
        {
          "type": "html",
          "visibleIf": "{send-results} = true",
          "html": {
            "default": "We look forward to getting your feedback. As a core Automation Kit team we use the feedback to improving our getting started guidance",
            "da": "Vi ser frem til at få din feedback. Som et centralt Automation Kit-team bruger vi feedbacken til at forbedre vores vejledning til at komme i gang"
          }
        },
        {
          "type": "comment",
          "name": "other-feedback",
          "title": {
            "default": "Did you have any other feedback?",
            "da": "Har du andre tilbagemeldinger?"
          },
          "visibleIf": "{send-results} = true"
        },
        {
          "type": "feedback-task",
          "name": "send-results",
          "title": {
            "default": "Send your feedback now?",
            "da": "Send din feedback nu?"
          },
          "destination": "https://aka.ms/ak4pp-feedback2",
          "visibleIf": "{send-results} = true"
        },
        {
          "type": "html",
          "visibleIf": "{send-results-status.length} > 0",
          "html": {
            "default": "Status: {send-results-status}",
            "da": "Status: "
          }
        }
      ]
    }
  ]
}