<?xml version="1.0" encoding="utf-8"?>
<WebResource xmlns:xsi="http://www.w3.org/2001/XMLSchema-instance">
  <WebResourceId>{88ad3bcf-e62a-ee11-bdf4-0022482b6e98}</WebResourceId>
  <Name>autocoe_auditsvg</Name>
  <DisplayName>audit icon</DisplayName>
  <WebResourceType>11</WebResourceType>
  <IntroducedVersion>1.0.0.8</IntroducedVersion>
  <IsEnabledForMobileClient>0</IsEnabledForMobileClient>
  <IsAvailableForMobileOffline>0</IsAvailableForMobileOffline>
  <IsCustomizable>1</IsCustomizable>
  <CanBeDeleted>1</CanBeDeleted>
  <IsHidden>0</IsHidden>
  <FileName>/WebResources/autocoe_auditsvg88AD3BCF-E62A-EE11-BDF4-0022482B6E98</FileName>
</WebResource>